setup.py
pisoc/__init__.py
pisoc/analog.py
pisoc/digital.py
pisoc.egg-info/PKG-INFO
pisoc.egg-info/SOURCES.txt
pisoc.egg-info/dependency_links.txt
pisoc.egg-info/requires.txt
pisoc.egg-info/top_level.txt