Metadata-Version: 1.0
Name: pisoc
Version: 2.0.1
Summary: PiSoC Python API
Home-page: UNKNOWN
Author: Brian Bradley
Author-email: bradley@embeditelectronics.com
License: MIT
Platform: UNKNOWN
